Metadata-Version: 2.4
Name: llama-index-llms-featherlessai
Version: 0.1.0
Summary: llama-index llms featherlessai integration
Author-email: Your Name <you@example.com>
License-Expression: MIT
License-File: LICENSE
Requires-Python: <4.0,>=3.9
Requires-Dist: llama-index-core<0.13,>=0.12.0
Requires-Dist: llama-index-llms-openai-like<0.4,>=0.3.1
